{
    "variants": {
        "moisture=7,snowy=false": { "model": "aestheticism:block/muddy_grass_7" },
        "moisture=6,snowy=false": { "model": "aestheticism:block/muddy_grass_6" },
        "moisture=5,snowy=false": { "model": "aestheticism:block/muddy_grass_5" },
        "moisture=4,snowy=false": { "model": "aestheticism:block/muddy_grass_4" },
        "moisture=3,snowy=false": { "model": "aestheticism:block/muddy_grass_3" },
        "moisture=2,snowy=false": { "model": "aestheticism:block/muddy_grass_2" },
        "moisture=1,snowy=false": { "model": "aestheticism:block/muddy_grass_1" }
    }
}
